odoo/addons/ssi_elearning_work_log/README.rst
odoo/addons/ssi_elearning_work_log/__init__.py
odoo/addons/ssi_elearning_work_log/__manifest__.py
odoo/addons/ssi_elearning_work_log/i18n/ssi_elearning_work_log.pot
odoo/addons/ssi_elearning_work_log/models/__init__.py
odoo/addons/ssi_elearning_work_log/models/slide_channel.py
odoo/addons/ssi_elearning_work_log/models/slide_slide.py
odoo/addons/ssi_elearning_work_log/static/description/icon.png
odoo14_addon_ssi_elearning_work_log-14.0.1.0.1.dev2.dist-info/METADATA
odoo14_addon_ssi_elearning_work_log-14.0.1.0.1.dev2.dist-info/WHEEL
odoo14_addon_ssi_elearning_work_log-14.0.1.0.1.dev2.dist-info/top_level.txt
odoo14_addon_ssi_elearning_work_log-14.0.1.0.1.dev2.dist-info/RECORD
